addon.py
bc3_writer.py
tools.py
iflow_mcp_bonsai_mcp-0.1.2.dist-info/licenses/LICENSE.md
iflow_mcp_bonsai_mcp-0.1.2.dist-info/METADATA
iflow_mcp_bonsai_mcp-0.1.2.dist-info/WHEEL
iflow_mcp_bonsai_mcp-0.1.2.dist-info/entry_points.txt
iflow_mcp_bonsai_mcp-0.1.2.dist-info/top_level.txt
iflow_mcp_bonsai_mcp-0.1.2.dist-info/RECORD
