Metadata-Version: 2.4
Name: iflow-mcp_bonsai-mcp
Version: 0.1.2
Summary: A minimal MCP Server to illusrate the interaction between Bonsai BIM (Blender) and Claude.
Author: JotaDeRodriguez
License: MIT
Project-URL: Homepage, https://github.com/JotaDeRodriguez/Bonsai_mcp
Project-URL: Bug Tracker, https://github.com/JotaDeRodriguez/Bonsai_mcp/issues
Requires-Python: >=3.10
License-File: LICENSE.md
Requires-Dist: httpx>=0.28.1
Requires-Dist: mcp[cli]>=1.4.1
Requires-Dist: pillow>=11.3.0
Dynamic: license-file
